{
    "name" : "student name",
    "class" : {
        "Monday" : {
            "820" : "",
            "1005" : "",
            "1255" : "",
            "1440" : ""
        },
        "Tuesday" : {
            "820" : "",
            "1005" : "",
            "1255" : "",
            "1440" : ""
        },
        "Wednesday" : {
            "820" : "",
            "1005" : "",
            "1255" : "",
            "1440" : ""
        },
        "Thursday" : {
            "820" : "",
            "1005" : "",
            "1255" : "",
            "1440" : ""
        },
        "Friday" : {
            "820" : "",
            "1005" : "",
            "1255" : "",
            "1440" : ""
        },
        "Saturday" : {
            "820" : "",
            "1005" : "",
            "1255" : "",
            "1440" : ""
        },
        "Sunday" : {
            "820" : "",
            "1005" : "",
            "1255" : "",
            "1440" : ""
        }
    }
}